v8serialize/__init__.py
v8serialize/_decorators.py
v8serialize/_enums.py
v8serialize/_errors.py
v8serialize/_pycompat/__init__.py
v8serialize/_pycompat/dataclasses.py
v8serialize/_pycompat/enum.py
v8serialize/_pycompat/exceptions.py
v8serialize/_pycompat/inspect.py
v8serialize/_pycompat/re.py
v8serialize/_pycompat/typing.py
v8serialize/_recursive_eq.py
v8serialize/_references.py
v8serialize/_typing.py
v8serialize/_values.py
v8serialize/_versions.py
v8serialize/constants.py
v8serialize/decode.py
v8serialize/encode.py
v8serialize/extensions.py
v8serialize/jstypes/__init__.py
v8serialize/jstypes/_equality.py
v8serialize/jstypes/_normalise_property_key.py
v8serialize/jstypes/_repr.py
v8serialize/jstypes/_v8.py
v8serialize/jstypes/_v8traceback.py
v8serialize/jstypes/jsarray.py
v8serialize/jstypes/jsarrayproperties.py
v8serialize/jstypes/jsbigint.py
v8serialize/jstypes/jsbuffers.py
v8serialize/jstypes/jserror.py
v8serialize/jstypes/jsmap.py
v8serialize/jstypes/jsobject.py
v8serialize/jstypes/jsprimitiveobject.py
v8serialize/jstypes/jsregexp.py
v8serialize/jstypes/jsset.py
v8serialize/jstypes/jsundefined.py
v8serialize/py.typed
v8serialize-0.4.0.dist-info/METADATA
v8serialize-0.4.0.dist-info/WHEEL
v8serialize-0.4.0.dist-info/licenses/LICENSE.md
v8serialize-0.4.0.dist-info/RECORD
