Metadata-Version: 2.4
Name: v8serialize
Version: 0.4.0
Summary: Read & write JavaScript values from Python with the V8 serialization format.
License: MIT
License-File: LICENSE.md
Author: Hal Blackburn
Author-email: hwtb2@cam.ac.uk
Requires-Python: >=3.10,<4.0
Classifier: License :: OSI Approved :: MIT License
Classifier: Programming Language :: Python :: 3
Classifier: Programming Language :: Python :: 3.10
Classifier: Programming Language :: Python :: 3.11
Classifier: Programming Language :: Python :: 3.12
Classifier: Programming Language :: Python :: 3.13
Classifier: Programming Language :: Python :: 3.14
Requires-Dist: packaging (>=14.5)
